regresseasy/__init__.py
regresseasy/main.py
regresseasy-0.7.dist-info/LICENSE
regresseasy-0.7.dist-info/METADATA
regresseasy-0.7.dist-info/WHEEL
regresseasy-0.7.dist-info/top_level.txt
regresseasy-0.7.dist-info/RECORD
