Metadata-Version: 2.1
Name: regresseasy
Version: 0.7
Summary: Regression Model Performances
Home-page: https://github.com/koushik2299/RegressEasy
Author: sai_koushik
Author-email: saikoushik.gsk@gmail.com
Classifier: Programming Language :: Python :: 3
Classifier: License :: OSI Approved :: MIT License
Classifier: Operating System :: OS Independent
Requires-Python: >=3.6
License-File: LICENSE
Requires-Dist: scikit-learn
Requires-Dist: pandas
Requires-Dist: numpy
